{"nm":"Comp 1","ddd":0,"h":1080,"w":1080,"meta":{"g":"@lottiefiles/toolkit-js 0.26.1"},"layers":[{"ty":4,"nm":"Shape Layer 5","sr":1,"st":0,"op":42,"ip":24,"hd":false,"ddd":0,"bm":0,"hasMask":false,"ao":0,"ks":{"a":{"a":0,"k":[0,0,0],"ix":1},"s":{"a":0,"k":[100,100,100],"ix":6},"sk":{"a":0,"k":0},"p":{"a":0,"k":[312,540,0],"ix":2},"r":{"a":0,"k":0,"ix":10},"sa":{"a":0,"k":0},"o":{"a":0,"k":100,"ix":11}},"ef":[],"shapes":[{"ty":"gr","bm":0,"hd":false,"mn":"ADBE Vector Group","nm":"Ellipse 1","ix":1,"cix":2,"np":2,"it":[{"ty":"el","bm":0,"hd":false,"mn":"ADBE Vector Shape - Ellipse","nm":"Ellipse Path 1","d":1,"p":{"a":0,"k":[0,0],"ix":3},"s":{"a":0,"k":[424,424],"ix":2}},{"ty":"st","bm":0,"hd":false,"mn":"ADBE Vector Graphic - Stroke","nm":"Stroke 1","lc":2,"lj":1,"ml":4,"o":{"a":0,"k":100,"ix":4},"w":{"a":0,"k":40,"ix":5},"c":{"a":0,"k":[0.102,0.4667,0.898],"ix":3}},{"ty":"tr","a":{"a":0,"k":[0,0],"ix":1},"s":{"a":0,"k":[100,100],"ix":3},"sk":{"a":0,"k":0,"ix":4},"p":{"a":0,"k":[259,29],"ix":2},"r":{"a":0,"k":0,"ix":6},"sa":{"a":0,"k":0,"ix":5},"o":{"a":0,"k":100,"ix":7}}]},{"ty":"tm","bm":0,"hd":false,"mn":"ADBE Vector Filter - Trim","nm":"Trim Paths 1","ix":2,"e":{"a":1,"k":[{"o":{"x":0.747,"y":0},"i":{"x":0.505,"y":1},"s":[12.6],"t":24.025},{"s":[100],"t":36.025390625}],"ix":2},"o":{"a":1,"k":[{"o":{"x":0.333,"y":0},"i":{"x":0.667,"y":1},"s":[-4],"t":24},{"s":[10.2],"t":39}],"ix":3},"s":{"a":1,"k":[{"o":{"x":0.747,"y":0},"i":{"x":0.505,"y":1},"s":[0],"t":30.025},{"s":[100],"t":42}],"ix":1},"m":2}],"ind":1},{"ty":4,"nm":"Shape Layer 4","sr":1,"st":-24,"op":24,"ip":0,"hd":false,"ddd":0,"bm":0,"hasMask":false,"ao":0,"ks":{"a":{"a":0,"k":[0,0,0],"ix":1},"s":{"a":0,"k":[100,100,100],"ix":6},"sk":{"a":0,"k":0},"p":{"a":0,"k":[312,540,0],"ix":2},"r":{"a":0,"k":0,"ix":10},"sa":{"a":0,"k":0},"o":{"a":0,"k":100,"ix":11}},"ef":[],"shapes":[{"ty":"gr","bm":0,"hd":false,"mn":"ADBE Vector Group","nm":"Ellipse 1","ix":1,"cix":2,"np":2,"it":[{"ty":"el","bm":0,"hd":false,"mn":"ADBE Vector Shape - Ellipse","nm":"Ellipse Path 1","d":1,"p":{"a":0,"k":[0,0],"ix":3},"s":{"a":0,"k":[424,424],"ix":2}},{"ty":"st","bm":0,"hd":false,"mn":"ADBE Vector Graphic - Stroke","nm":"Stroke 1","lc":2,"lj":1,"ml":4,"o":{"a":0,"k":100,"ix":4},"w":{"a":0,"k":40,"ix":5},"c":{"a":0,"k":[0.102,0.4667,0.898],"ix":3}},{"ty":"tr","a":{"a":0,"k":[0,0],"ix":1},"s":{"a":0,"k":[100,100],"ix":3},"sk":{"a":0,"k":0,"ix":4},"p":{"a":0,"k":[259,29],"ix":2},"r":{"a":0,"k":0,"ix":6},"sa":{"a":0,"k":0,"ix":5},"o":{"a":0,"k":100,"ix":7}}]},{"ty":"tm","bm":0,"hd":false,"mn":"ADBE Vector Filter - Trim","nm":"Trim Paths 1","ix":2,"e":{"a":1,"k":[{"o":{"x":0.667,"y":0},"i":{"x":0.502,"y":1},"s":[0],"t":5},{"o":{"x":0.333,"y":0},"i":{"x":0.833,"y":1},"s":[100],"t":17},{"s":[100],"t":24}],"ix":2},"o":{"a":1,"k":[{"o":{"x":0.167,"y":0},"i":{"x":0.667,"y":1},"s":[374.5],"t":5},{"o":{"x":0.333,"y":0},"i":{"x":0.667,"y":1},"s":[374.5],"t":17},{"s":[401.5],"t":24}],"ix":3},"s":{"a":1,"k":[{"o":{"x":0.692,"y":0},"i":{"x":0.712,"y":0.693},"s":[0],"t":11},{"s":[87.425],"t":20}],"ix":1},"m":2}],"ind":2},{"ty":4,"nm":"lingkaran luar Outlines 3","sr":1,"st":0,"op":42,"ip":24,"hd":false,"ddd":0,"bm":0,"hasMask":false,"ao":0,"ks":{"a":{"a":0,"k":[312.99,312.989,0],"ix":1},"s":{"a":0,"k":[100,100,100],"ix":6},"sk":{"a":0,"k":0},"p":{"a":0,"k":[570.62,569.182,0],"ix":2},"r":{"a":0,"k":0,"ix":10},"sa":{"a":0,"k":0},"o":{"a":0,"k":100,"ix":11}},"ef":[],"shapes":[{"ty":"gr","bm":0,"hd":false,"mn":"ADBE Vector Group","nm":"Group 1","ix":1,"cix":2,"np":2,"it":[{"ty":"sh","bm":0,"hd":false,"mn":"ADBE Vector Shape - Group","nm":"Path 1","ix":1,"d":1,"ks":{"a":0,"k":{"c":true,"i":[[0,-112.095],[117.63,0],[0,117.631],[-117.631,0],[-5.43,-0.415]],"o":[[0,117.631],[-117.631,0],[0,-117.631],[5.536,0],[109.943,8.398]],"v":[[212.99,0],[0,212.989],[-212.99,0],[0,-212.989],[16.452,-212.363]]},"ix":2}},{"ty":"st","bm":0,"hd":false,"mn":"ADBE Vector Graphic - Stroke","nm":"Stroke 1","lc":2,"lj":2,"ml":1,"o":{"a":0,"k":100,"ix":4},"w":{"a":0,"k":40,"ix":5},"c":{"a":0,"k":[0.102,0.4667,0.898],"ix":3}},{"ty":"tr","a":{"a":0,"k":[0,0],"ix":1},"s":{"a":0,"k":[100,100],"ix":3},"sk":{"a":0,"k":0,"ix":4},"p":{"a":0,"k":[312.99,312.989],"ix":2},"r":{"a":0,"k":0,"ix":6},"sa":{"a":0,"k":0,"ix":5},"o":{"a":0,"k":100,"ix":7}}]},{"ty":"tm","bm":0,"hd":false,"mn":"ADBE Vector Filter - Trim","nm":"Trim Paths 1","ix":2,"e":{"a":1,"k":[{"o":{"x":0.747,"y":0},"i":{"x":0.505,"y":1},"s":[12.6],"t":24.025},{"s":[100],"t":36.025390625}],"ix":2},"o":{"a":1,"k":[{"o":{"x":0.333,"y":0},"i":{"x":0.667,"y":1},"s":[-94],"t":24},{"s":[-79.8],"t":39}],"ix":3},"s":{"a":1,"k":[{"o":{"x":0.747,"y":0},"i":{"x":0.505,"y":1},"s":[0],"t":30.025},{"s":[100],"t":42}],"ix":1},"m":2}],"ind":3},{"ty":4,"nm":"lingkaran luar Outlines 2","sr":1,"st":0,"op":24,"ip":0,"hd":false,"ddd":0,"bm":0,"hasMask":false,"ao":0,"ks":{"a":{"a":0,"k":[312.99,312.989,0],"ix":1},"s":{"a":0,"k":[100,100,100],"ix":6},"sk":{"a":0,"k":0},"p":{"a":0,"k":[570.62,569.182,0],"ix":2},"r":{"a":0,"k":0,"ix":10},"sa":{"a":0,"k":0},"o":{"a":0,"k":100,"ix":11}},"ef":[],"shapes":[{"ty":"gr","bm":0,"hd":false,"mn":"ADBE Vector Group","nm":"Group 1","ix":1,"cix":2,"np":2,"it":[{"ty":"sh","bm":0,"hd":false,"mn":"ADBE Vector Shape - Group","nm":"Path 1","ix":1,"d":1,"ks":{"a":0,"k":{"c":true,"i":[[0,-112.095],[117.63,0],[0,117.631],[-117.631,0],[-5.43,-0.415]],"o":[[0,117.631],[-117.631,0],[0,-117.631],[5.536,0],[109.943,8.398]],"v":[[212.99,0],[0,212.989],[-212.99,0],[0,-212.989],[16.452,-212.363]]},"ix":2}},{"ty":"st","bm":0,"hd":false,"mn":"ADBE Vector Graphic - Stroke","nm":"Stroke 1","lc":2,"lj":2,"ml":1,"o":{"a":0,"k":100,"ix":4},"w":{"a":0,"k":40,"ix":5},"c":{"a":0,"k":[0.102,0.4667,0.898],"ix":3}},{"ty":"tr","a":{"a":0,"k":[0,0],"ix":1},"s":{"a":0,"k":[100,100],"ix":3},"sk":{"a":0,"k":0,"ix":4},"p":{"a":0,"k":[312.99,312.989],"ix":2},"r":{"a":0,"k":0,"ix":6},"sa":{"a":0,"k":0,"ix":5},"o":{"a":0,"k":100,"ix":7}}]},{"ty":"tm","bm":0,"hd":false,"mn":"ADBE Vector Filter - Trim","nm":"Trim Paths 1","ix":2,"e":{"a":1,"k":[{"o":{"x":0.667,"y":0},"i":{"x":0.502,"y":1},"s":[0],"t":5},{"o":{"x":0.333,"y":0},"i":{"x":0.833,"y":1},"s":[100],"t":17},{"s":[100],"t":24}],"ix":2},"o":{"a":1,"k":[{"o":{"x":0.167,"y":0},"i":{"x":0.667,"y":1},"s":[284.5],"t":5},{"o":{"x":0.333,"y":0},"i":{"x":0.667,"y":1},"s":[284.5],"t":17},{"s":[311.5],"t":24}],"ix":3},"s":{"a":1,"k":[{"o":{"x":0.692,"y":0},"i":{"x":0.712,"y":0.693},"s":[0],"t":11},{"s":[87.425],"t":20}],"ix":1},"m":2}],"ind":4},{"ty":4,"nm":"Shape Layer 1","sr":1,"st":0,"op":721,"ip":0,"hd":false,"ddd":0,"bm":0,"hasMask":false,"td":1,"ao":0,"ks":{"a":{"a":0,"k":[0,0,0],"ix":1},"s":{"a":0,"k":[100,100,100],"ix":6},"sk":{"a":0,"k":0},"p":{"a":0,"k":[540,540,0],"ix":2},"r":{"a":0,"k":0,"ix":10},"sa":{"a":0,"k":0},"o":{"a":0,"k":100,"ix":11}},"ef":[],"shapes":[{"ty":"gr","bm":0,"hd":false,"mn":"ADBE Vector Group","nm":"Shape 1","ix":1,"cix":2,"np":3,"it":[{"ty":"sh","bm":0,"hd":false,"mn":"ADBE Vector Shape - Group","nm":"Path 1","ix":1,"d":1,"ks":{"a":1,"k":[{"o":{"x":0.167,"y":0.167},"i":{"x":0.833,"y":0.833},"s":[{"c":true,"i":[[7.878,-1.32],[0,0],[0,0],[-6,4],[0,0],[0,0],[16.218,2.999]],"o":[[-23.125,3.875],[0,0],[0,0],[6,-4],[0,0],[0,0],[-8.379,-1.549]],"v":[[58.125,-198.25],[-136,-118],[-158,30],[-72,46],[82,-78],[113.625,-188.25],[83.333,-197.281]]}],"t":24},{"s":[{"c":true,"i":[[6.065,-1.016],[0,0],[0,0],[-6,4],[0,0],[0,0],[19.147,11.207]],"o":[[-23.125,3.875],[0,0],[0,0],[6,-4],[0,0],[0,0],[-5.732,-3.355]],"v":[[58.125,-198.25],[-136,-118],[-158,30],[-72,46],[82,-78],[84.75,-168],[77.478,-198.207]]}],"t":36}],"ix":2}},{"ty":"st","bm":0,"hd":false,"mn":"ADBE Vector Graphic - Stroke","nm":"Stroke 1","lc":1,"lj":1,"ml":4,"o":{"a":0,"k":100,"ix":4},"w":{"a":0,"k":0,"ix":5},"c":{"a":0,"k":[0.749,0.5333,0.3216],"ix":3}},{"ty":"fl","bm":0,"hd":false,"mn":"ADBE Vector Graphic - Fill","nm":"Fill 1","c":{"a":0,"k":[1,0.1882,0.4549],"ix":4},"r":1,"o":{"a":0,"k":100,"ix":5}},{"ty":"tr","a":{"a":0,"k":[0,0],"ix":1},"s":{"a":0,"k":[100,100],"ix":3},"sk":{"a":0,"k":0,"ix":4},"p":{"a":0,"k":[0,0],"ix":2},"r":{"a":0,"k":0,"ix":6},"sa":{"a":0,"k":0,"ix":5},"o":{"a":0,"k":100,"ix":7}}]}],"ind":5},{"ty":4,"nm":"biru kiri Outlines","sr":1,"st":0,"op":721,"ip":0,"hd":false,"ddd":0,"bm":0,"tt":1,"hasMask":false,"ao":0,"ks":{"a":{"a":0,"k":[190.518,190.538,0],"ix":1},"s":{"a":0,"k":[100,100,100],"ix":6},"sk":{"a":0,"k":0},"p":{"a":0,"k":[517.567,450.016,0],"ix":2},"r":{"a":0,"k":0,"ix":10},"sa":{"a":0,"k":0},"o":{"a":0,"k":100,"ix":11}},"ef":[],"shapes":[{"ty":"gr","bm":0,"hd":false,"mn":"ADBE Vector Group","nm":"Group 1","ix":1,"cix":2,"np":2,"it":[{"ty":"sh","bm":0,"hd":false,"mn":"ADBE Vector Shape - Group","nm":"Path 1","ix":1,"d":1,"ks":{"a":0,"k":{"c":false,"i":[[0,0],[0,0]],"o":[[0,0],[0,0]],"v":[[257.018,-256.539],[-90.518,90.539]]},"ix":2}},{"ty":"st","bm":0,"hd":false,"mn":"ADBE Vector Graphic - Stroke","nm":"Stroke 1","lc":2,"lj":2,"ml":1,"o":{"a":0,"k":100,"ix":4},"w":{"a":0,"k":40,"ix":5},"c":{"a":0,"k":[0.102,0.4667,0.898],"ix":3}},{"ty":"tr","a":{"a":0,"k":[0,0],"ix":1},"s":{"a":0,"k":[100,100],"ix":3},"sk":{"a":0,"k":0,"ix":4},"p":{"a":0,"k":[190.518,190.539],"ix":2},"r":{"a":0,"k":0,"ix":6},"sa":{"a":0,"k":0,"ix":5},"o":{"a":0,"k":100,"ix":7}}]},{"ty":"tm","bm":0,"hd":false,"mn":"ADBE Vector Filter - Trim","nm":"Trim Paths 1","ix":2,"e":{"a":0,"k":100,"ix":2},"o":{"a":1,"k":[{"o":{"x":0.333,"y":0},"i":{"x":0.667,"y":1},"s":[0],"t":0},{"o":{"x":0.333,"y":0},"i":{"x":0.667,"y":1},"s":[-223],"t":12},{"o":{"x":0.333,"y":0},"i":{"x":0.336,"y":1},"s":[-223],"t":36},{"s":[0],"t":48}],"ix":3},"s":{"a":0,"k":67,"ix":1},"m":1}],"ind":6},{"ty":4,"nm":"kotak dalem Outlines 5","sr":1,"st":24,"op":54,"ip":24,"hd":false,"ddd":0,"bm":0,"hasMask":false,"ao":0,"ks":{"a":{"a":0,"k":[185.958,185.957,0],"ix":1},"s":{"a":0,"k":[100,100,100],"ix":6},"sk":{"a":0,"k":0},"p":{"a":0,"k":[570.678,569.261,0],"ix":2},"r":{"a":0,"k":0,"ix":10},"sa":{"a":0,"k":0},"o":{"a":0,"k":100,"ix":11}},"ef":[],"shapes":[{"ty":"gr","bm":0,"hd":false,"mn":"ADBE Vector Group","nm":"Group 1","ix":1,"cix":2,"np":2,"it":[{"ty":"sh","bm":0,"hd":false,"mn":"ADBE Vector Shape - Group","nm":"Path 1","ix":1,"d":1,"ks":{"a":0,"k":{"c":true,"i":[[0,0],[0,0],[0,0],[0,0]],"o":[[0,0],[0,0],[0,0],[0,0]],"v":[[-28.625,85.957],[-85.957,28.625],[28.626,-85.957],[85.957,-28.625]]},"ix":2}},{"ty":"st","bm":0,"hd":false,"mn":"ADBE Vector Graphic - Stroke","nm":"Stroke 1","lc":2,"lj":2,"ml":1,"o":{"a":0,"k":100,"ix":4},"w":{"a":0,"k":40,"ix":5},"c":{"a":0,"k":[0.102,0.4667,0.898],"ix":3}},{"ty":"tr","a":{"a":0,"k":[0,0],"ix":1},"s":{"a":0,"k":[100,100],"ix":3},"sk":{"a":0,"k":0,"ix":4},"p":{"a":0,"k":[185.958,185.958],"ix":2},"r":{"a":0,"k":0,"ix":6},"sa":{"a":0,"k":0,"ix":5},"o":{"a":0,"k":100,"ix":7}}]},{"ty":"tm","bm":0,"hd":false,"mn":"ADBE Vector Filter - Trim","nm":"Trim Paths 1","ix":2,"e":{"a":0,"k":83,"ix":2},"o":{"a":1,"k":[{"o":{"x":0.672,"y":0},"i":{"x":0.833,"y":0.833},"s":[181],"t":24},{"o":{"x":0.167,"y":0.167},"i":{"x":0.667,"y":1},"s":[363],"t":36},{"s":[542],"t":48}],"ix":3},"s":{"a":0,"k":50,"ix":1},"m":1}],"ind":7},{"ty":4,"nm":"kotak dalem Outlines 4","sr":1,"st":0,"op":24,"ip":0,"hd":false,"ddd":0,"bm":0,"hasMask":false,"ao":0,"ks":{"a":{"a":0,"k":[185.958,185.957,0],"ix":1},"s":{"a":0,"k":[100,100,100],"ix":6},"sk":{"a":0,"k":0},"p":{"a":0,"k":[570.678,569.261,0],"ix":2},"r":{"a":0,"k":0,"ix":10},"sa":{"a":0,"k":0},"o":{"a":0,"k":100,"ix":11}},"ef":[],"shapes":[{"ty":"gr","bm":0,"hd":false,"mn":"ADBE Vector Group","nm":"Group 1","ix":1,"cix":2,"np":2,"it":[{"ty":"sh","bm":0,"hd":false,"mn":"ADBE Vector Shape - Group","nm":"Path 1","ix":1,"d":1,"ks":{"a":0,"k":{"c":true,"i":[[0,0],[0,0],[0,0],[0,0]],"o":[[0,0],[0,0],[0,0],[0,0]],"v":[[-28.625,85.957],[-85.957,28.625],[28.626,-85.957],[85.957,-28.625]]},"ix":2}},{"ty":"st","bm":0,"hd":false,"mn":"ADBE Vector Graphic - Stroke","nm":"Stroke 1","lc":2,"lj":2,"ml":1,"o":{"a":0,"k":100,"ix":4},"w":{"a":0,"k":40,"ix":5},"c":{"a":0,"k":[0.102,0.4667,0.898],"ix":3}},{"ty":"tr","a":{"a":0,"k":[0,0],"ix":1},"s":{"a":0,"k":[100,100],"ix":3},"sk":{"a":0,"k":0,"ix":4},"p":{"a":0,"k":[185.958,185.958],"ix":2},"r":{"a":0,"k":0,"ix":6},"sa":{"a":0,"k":0,"ix":5},"o":{"a":0,"k":100,"ix":7}}]},{"ty":"tm","bm":0,"hd":false,"mn":"ADBE Vector Filter - Trim","nm":"Trim Paths 1","ix":2,"e":{"a":0,"k":83,"ix":2},"o":{"a":1,"k":[{"o":{"x":0.672,"y":0},"i":{"x":0.833,"y":0.833},"s":[181],"t":0},{"o":{"x":0.167,"y":0.167},"i":{"x":0.667,"y":1},"s":[363],"t":12},{"s":[542],"t":24}],"ix":3},"s":{"a":0,"k":50,"ix":1},"m":1}],"ind":8},{"ty":4,"nm":"kotak dalem Outlines 3","sr":1,"st":24,"op":54,"ip":24,"hd":false,"ddd":0,"bm":0,"hasMask":false,"ao":0,"ks":{"a":{"a":0,"k":[185.958,185.957,0],"ix":1},"s":{"a":0,"k":[100,100,100],"ix":6},"sk":{"a":0,"k":0},"p":{"a":0,"k":[570.678,569.261,0],"ix":2},"r":{"a":0,"k":0,"ix":10},"sa":{"a":0,"k":0},"o":{"a":0,"k":100,"ix":11}},"ef":[],"shapes":[{"ty":"gr","bm":0,"hd":false,"mn":"ADBE Vector Group","nm":"Group 1","ix":1,"cix":2,"np":2,"it":[{"ty":"sh","bm":0,"hd":false,"mn":"ADBE Vector Shape - Group","nm":"Path 1","ix":1,"d":1,"ks":{"a":0,"k":{"c":true,"i":[[0,0],[0,0],[0,0],[0,0]],"o":[[0,0],[0,0],[0,0],[0,0]],"v":[[-28.625,85.957],[-85.957,28.625],[28.626,-85.957],[85.957,-28.625]]},"ix":2}},{"ty":"st","bm":0,"hd":false,"mn":"ADBE Vector Graphic - Stroke","nm":"Stroke 1","lc":2,"lj":2,"ml":1,"o":{"a":0,"k":100,"ix":4},"w":{"a":0,"k":40,"ix":5},"c":{"a":0,"k":[0.8588,0.1333,0.4078],"ix":3}},{"ty":"tr","a":{"a":0,"k":[0,0],"ix":1},"s":{"a":0,"k":[100,100],"ix":3},"sk":{"a":0,"k":0,"ix":4},"p":{"a":0,"k":[185.958,185.958],"ix":2},"r":{"a":0,"k":0,"ix":6},"sa":{"a":0,"k":0,"ix":5},"o":{"a":0,"k":100,"ix":7}}]},{"ty":"tm","bm":0,"hd":false,"mn":"ADBE Vector Filter - Trim","nm":"Trim Paths 1","ix":2,"e":{"a":0,"k":83,"ix":2},"o":{"a":1,"k":[{"o":{"x":0.672,"y":0},"i":{"x":0.833,"y":0.833},"s":[0],"t":24},{"o":{"x":0.167,"y":0.167},"i":{"x":0.667,"y":1},"s":[182],"t":36},{"s":[361],"t":48}],"ix":3},"s":{"a":0,"k":50,"ix":1},"m":1}],"ind":9},{"ty":4,"nm":"kotak dalem Outlines 2","sr":1,"st":0,"op":24,"ip":0,"hd":false,"ddd":0,"bm":0,"hasMask":false,"ao":0,"ks":{"a":{"a":0,"k":[185.958,185.957,0],"ix":1},"s":{"a":0,"k":[100,100,100],"ix":6},"sk":{"a":0,"k":0},"p":{"a":0,"k":[570.678,569.261,0],"ix":2},"r":{"a":0,"k":0,"ix":10},"sa":{"a":0,"k":0},"o":{"a":0,"k":100,"ix":11}},"ef":[],"shapes":[{"ty":"gr","bm":0,"hd":false,"mn":"ADBE Vector Group","nm":"Group 1","ix":1,"cix":2,"np":2,"it":[{"ty":"sh","bm":0,"hd":false,"mn":"ADBE Vector Shape - Group","nm":"Path 1","ix":1,"d":1,"ks":{"a":0,"k":{"c":true,"i":[[0,0],[0,0],[0,0],[0,0]],"o":[[0,0],[0,0],[0,0],[0,0]],"v":[[-28.625,85.957],[-85.957,28.625],[28.626,-85.957],[85.957,-28.625]]},"ix":2}},{"ty":"st","bm":0,"hd":false,"mn":"ADBE Vector Graphic - Stroke","nm":"Stroke 1","lc":2,"lj":2,"ml":1,"o":{"a":0,"k":100,"ix":4},"w":{"a":0,"k":40,"ix":5},"c":{"a":0,"k":[0.8588,0.1333,0.4078],"ix":3}},{"ty":"tr","a":{"a":0,"k":[0,0],"ix":1},"s":{"a":0,"k":[100,100],"ix":3},"sk":{"a":0,"k":0,"ix":4},"p":{"a":0,"k":[185.958,185.958],"ix":2},"r":{"a":0,"k":0,"ix":6},"sa":{"a":0,"k":0,"ix":5},"o":{"a":0,"k":100,"ix":7}}]},{"ty":"tm","bm":0,"hd":false,"mn":"ADBE Vector Filter - Trim","nm":"Trim Paths 1","ix":2,"e":{"a":0,"k":83,"ix":2},"o":{"a":1,"k":[{"o":{"x":0.672,"y":0},"i":{"x":0.833,"y":0.833},"s":[0],"t":0},{"o":{"x":0.167,"y":0.167},"i":{"x":0.667,"y":1},"s":[182],"t":12},{"s":[361],"t":24}],"ix":3},"s":{"a":0,"k":50,"ix":1},"m":1}],"ind":10},{"ty":1,"nm":"White Solid 1","sr":1,"st":0,"op":721,"ip":0,"hd":false,"ddd":0,"bm":0,"hasMask":false,"ao":0,"ks":{"a":{"a":0,"k":[540,540,0],"ix":1},"s":{"a":0,"k":[100,100,100],"ix":6},"sk":{"a":0,"k":0},"p":{"a":0,"k":[540,540,0],"ix":2},"r":{"a":0,"k":0,"ix":10},"sa":{"a":0,"k":0},"o":{"a":0,"k":100,"ix":11}},"ef":[],"sc":"#ffffff","sh":1080,"sw":1080,"ind":11}],"v":"5.5.2","fr":24,"op":54,"ip":0,"assets":[]}